exam_proctor/__init__.py
exam_proctor/__main__.py
exam_proctor/bootstrap.py
exam_proctor/glb.py
exam_proctor/models.py
exam_proctor/permissions.py
exam_proctor/processes.py
exam_proctor/templates/base.html
exam_proctor/templates/confirm.html
exam_proctor/templates/message.html
exam_proctor/templates/privacy.html
exam_proctor/templates/start.html
exam_proctor/templates/status.html
exam_proctor/updater.py
exam_proctor/user-graduate.png
exam_proctor/user-graduate.svg
exam_proctor/utils.py
exam_proctor/video.py
exam_proctor/video_uploader.py
exam_proctor/web.py
exam_proctor/webcam.py
exam_proctor-0.3.0.dist-info/entry_points.txt
exam_proctor-0.3.0.dist-info/WHEEL
exam_proctor-0.3.0.dist-info/METADATA
exam_proctor-0.3.0.dist-info/RECORD
