Metadata-Version: 2.1
Name: exam-proctor
Version: 0.3.0
Summary: 
Author: Luca Allulli
Author-email: luca@skeed.it
Requires-Python: >=3.6,<4.0
Classifier: Programming Language :: Python :: 3
Classifier: Programming Language :: Python :: 3.6
Classifier: Programming Language :: Python :: 3.7
Classifier: Programming Language :: Python :: 3.8
Requires-Dist: bottle (>=0.12.18,<0.13.0)
Requires-Dist: ffsend (>=0.1.3,<0.2.0)
Requires-Dist: ipython (>=7.13.0,<8.0.0)
Requires-Dist: mss (>=5.0.0,<6.0.0)
Requires-Dist: opencv-python (>=4.2.0,<5.0.0)
Requires-Dist: peewee (>=3.13.2,<4.0.0)
Requires-Dist: psutil (>=5.7.0,<6.0.0)
Requires-Dist: pystray (>=0.15.0,<0.16.0)
Requires-Dist: python-ffmpeg (>=1.0.11,<2.0.0)
Requires-Dist: requests (>=2.23.0,<3.0.0)
Requires-Dist: waitress (>=1.4.3,<2.0.0)
